auspost_pac/__init__.py
auspost_pac/models.py
auspost_pac/pac.py
auspost_pac/tests.py
python_auspost_pac-1.0.2.dist-info/DESCRIPTION.rst
python_auspost_pac-1.0.2.dist-info/METADATA
python_auspost_pac-1.0.2.dist-info/RECORD
python_auspost_pac-1.0.2.dist-info/WHEEL
python_auspost_pac-1.0.2.dist-info/metadata.json
python_auspost_pac-1.0.2.dist-info/top_level.txt
