Metadata-Version: 2.0
Name: python-auspost-pac
Version: 1.0.2
Summary: Python API for Australia Post's Postage Assessment Calculator (pac).
Home-page: https://github.com/sjkingo/python-auspost-pac
Author: Sam Kingston
Author-email: sam@sjkwi.com.au
License: BSD
Platform: UNKNOWN
Classifier: Development Status :: 4 - Beta
Classifier: Environment :: Web Environment
Classifier: Intended Audience :: Developers
Classifier: License :: OSI Approved :: BSD License
Classifier: Operating System :: OS Independent
Classifier: Programming Language :: Python :: 3.3
Classifier: Programming Language :: Python :: 3.4
Classifier: Programming Language :: Python
Requires-Dist: cached-property
Requires-Dist: frozendict
Requires-Dist: requests
